{
    "entries": [
      {"text": "Mischief"},
      {"text": "Contraption"},
      {"text": "Eating"},
      {"text": "Body Heat"},
      {"text": "Napping"},
      {"text": "Sunbathing"},
      {"text": "Swimming"},
      {"text": "Skittering"},
      {"text": "Hunting"},
      {"text": "Scouting with Gav"},
      {"text": "\"Helping\""},
      {"text": "Heating Blackthorn's furnace"},
      {"text": "Helping Cid with ledgers"},
      {"text": "Costumes / Outfits"},
      {"text": "Helping Mid with a project"},
      {"text": "Sleeping in the rafters"},
      {"text": "Accidental? Arson"},
      {"text": "Velcro / Clingy"},
      {"text": "Ambrosia"},
      {"text": "Torgal Adventure"},
      {"text": "Torgal Mishaps"},
      {"text": "No Eat Lizzer!"},
      {"text": "Lizzer, No Eat!"},
      {"text": "Shenanigans"},
      {"text": "Tail loss"},
      {"text": "Chameleon"},
      {"text": "Eikon Abilities"},
      {"text": "New Friends"},
      {"text": "Befriending Monsters"}
    ]
}